README.rst
setup.cfg
setup.py
particulate/particulate.py
particulate.egg-info/PKG-INFO
particulate.egg-info/SOURCES.txt
particulate.egg-info/dependency_links.txt
particulate.egg-info/requires.txt
particulate.egg-info/top_level.txt
test/test_particulate.py